nonebot_plugin_searchBiliInfo/__init__.py
nonebot_plugin_searchBiliInfo/data.py
nonebot_plugin_searchBiliInfo/data_medal.py
nonebot_plugin_searchBiliInfo/html/composition_page.html
nonebot_plugin_searchbiliinfo-1.8.1.dist-info/LICENSE
nonebot_plugin_searchbiliinfo-1.8.1.dist-info/METADATA
nonebot_plugin_searchbiliinfo-1.8.1.dist-info/WHEEL
nonebot_plugin_searchbiliinfo-1.8.1.dist-info/RECORD
